Workbook

Sheet 說明
A1: 事件與成就目錄（繁體中文）
A2: 與 docs/events_and_achievements.md 內容相同；本表為可篩選的資料版本。數字以資料檔為準。
A4: 來源檔
A5: js/data/events.js | B5: 天氣 WEATHER、原始隨機事件 RANDOM_EVENTS（15）、醫病溝通兩難 DILEMMAS（12）、社區活動 COMMUNITY（7）、衛教看板 BOARDS（7）
A6: js/data/events_ext.js | B6: 擴充事件 EVENTS_EXT_A（30：健保營運 14、病患與溝通 16）
A7: js/data/events_ext2.js | B7: 擴充事件 EVENTS_EXT_B（28：診所營運 16、季節與在地 12）
A8: js/data/achievements.js | B8: 成就 ACHIEVEMENTS（41）、階層獎勵 ACHIEVEMENT_TIERS
A9: docs/EVENTS_EXT.md §1–2 | B9: 效果欄位與條件欄位的定義
A10: js/sim/events.js 等 | B10: 引擎常數（每週機率、間隔、權重、冷卻）與連鎖、擲骰規則
A12: 數量核對（公式依各分頁即時計算）
A13: 項目 | B13: 數量（公式） | C13: 應為（資料檔） | D13: 核對
A14: 隨機事件（全部） | B14: =COUNTA(事件!C2:C74) -> 73 | C14: 73 | D14: =IF(B14=C14,"符合","不符，請檢查") -> 符合
A15: 原始（events.js） | B15: =COUNTIF(事件!B2:B74,"原始（events.js）") -> 15 | C15: 15 | D15: =IF(B15=C15,"符合","不符，請檢查") -> 符合
A16: 擴充（events_ext.js） | B16: =COUNTIF(事件!B2:B74,"擴充（events_ext.js）") -> 30 | C16: 30 | D16: =IF(B16=C16,"符合","不符，請檢查") -> 符合
A17: 擴充（events_ext2.js） | B17: =COUNTIF(事件!B2:B74,"擴充（events_ext2.js）") -> 28 | C17: 28 | D17: =IF(B17=C17,"符合","不符，請檢查") -> 符合
A18: 分類：一般 | B18: =COUNTIF(事件!A2:A74,"一般") -> 12 | C18: 12 | D18: =IF(B18=C18,"符合","不符，請檢查") -> 符合
A19: 分類：健保營運 | B19: =COUNTIF(事件!A2:A74,"健保營運") -> 15 | C19: 15 | D19: =IF(B19=C19,"符合","不符，請檢查") -> 符合
A20: 分類：病患與溝通 | B20: =COUNTIF(事件!A2:A74,"病患與溝通") -> 16 | C20: 16 | D20: =IF(B20=C20,"符合","不符，請檢查") -> 符合
A21: 分類：診所營運 | B21: =COUNTIF(事件!A2:A74,"診所營運") -> 17 | C21: 17 | D21: =IF(B21=C21,"符合","不符，請檢查") -> 符合
A22: 分類：季節與在地 | B22: =COUNTIF(事件!A2:A74,"季節與在地") -> 13 | C22: 13 | D22: =IF(B22=C22,"符合","不符，請檢查") -> 符合
A23: 大事件（隨機事件中） | B23: =COUNTIF(事件!F2:F74,"是") -> 14 | C23: 14 | D23: =IF(B23=C23,"符合","不符，請檢查") -> 符合
A24: 醫病溝通兩難 | B24: =COUNTA(醫病溝通兩難!B2:B13) -> 12 | C24: 12 | D24: =IF(B24=C24,"符合","不符，請檢查") -> 符合
A25: 天氣 | B25: =COUNTA(天氣!B2:B8) -> 7 | C25: 7 | D25: =IF(B25=C25,"符合","不符，請檢查") -> 符合
A26: 社區活動 | B26: =COUNTA(社區活動!B2:B8) -> 7 | C26: 7 | D26: =IF(B26=C26,"符合","不符，請檢查") -> 符合
A27: 衛教看板 | B27: =COUNTA(衛教看板!B2:B8) -> 7 | C27: 7 | D27: =IF(B27=C27,"符合","不符，請檢查") -> 符合
A28: 成就 | B28: =COUNTA(成就!C2:C42) -> 41 | C28: 41 | D28: =IF(B28=C28,"符合","不符，請檢查") -> 符合
A29: 隱藏成就 | B29: =COUNTIF(成就!N2:N42,"是") -> 4 | C29: 4 | D29: =IF(B29=C29,"符合","不符，請檢查") -> 符合
A30: 成就：獎勵資金合計（NT$，全部領取時） | B30: =SUM(成就!G2:G42) -> 1815000 | C30: — | D30: 成就獎勵合計（僅供參考）
A32: 欄位說明
A33: 「選項」欄：【選項文字】、效果（以「、」分隔，資金單位 NT$）、結果。擲骰選項會列出成功與失敗兩側。
A34: 效果用語：資金 ±NT$；聲譽 ±；病患滿意度 ±（隨機事件為全診所，醫病溝通兩難為當事病患）；健保點數 −；點數（醫術／儀器／服務）±；審查風險 ±（0–100，越低越好）；網路評價 ±（1.0–5.0）。
A35: 「抽選權重」與「冷卻（週）」：權重未標示者為引擎預設（一般 6、季節 10、大事件 3）；冷卻未標示者為預設（原始 20、擴充 24）。1 月 = 4 週。
A36: 「連鎖與旗標」欄：列出該事件的選項會設定的旗標或連鎖事件，以及哪些事件會把它當作前置。
A37: 成就「獎勵」依階層預設：銅 資金 NT$ 10,000、點數 8；銀 資金 NT$ 35,000、聲譽 +3、點數 15；金 資金 NT$ 150,000、聲譽 +10、點數 30。點數種類預設服務，少數成就指定醫術或儀器；金階一律服務。
A38: 隱藏成就在未解鎖時顯示「？？？」與提示，此表列出真實條件以便查閱。

Sheet 事件
A1: 分類 | B1: 來源 | C1: id | D1: 標題 | E1: 觸發條件 | F1: 大事件 | G1: 抽選權重 | H1: 冷卻（週） | I1: 情境 | J1: 選項1 | K1: 選項2 | L1: 選項3 | M1: 連鎖與旗標
A2: 一般 | B2: 原始（events.js） | C2: li_chief | D2: 里長邀約 | E2: 無條件（隨時可能出現） | F2: 否 | G2: 10 | H2: 20 | I2: 里長打電話來：「醫生啊，里民活動中心下禮拜要辦健康日，你們來擺個攤？」 | J2: 【好啊，免費幫大家篩檢】 效果：資金 −NT$ 120,000、聲譽 +8、服務點數 +10 結果：里民排成一排量血壓，里長笑到合不攏嘴，說要幫你們寫進里刊。 | K2: 【婉拒，我們診所忙不過來】 效果：聲譽 −2 結果：里長嘆氣說：「好啦，那下次再說喔。」下次就不知道是哪一次了。 | M2: —
A3: 健保營運 | B3: 原始（events.js） | C3: nhi_audit | D3: 健保署抽審 | E3: 第 1 年起（開業即符合） | F3: 是 | G3: 8 | H3: 20 | I3: 健保署來函，要抽調上個月的病歷和申報資料。信封很厚，主任的表情很薄。 | J3: 【配合調閱，全力準備】 效果：資金 −NT$ 80,000、聲譽 +3、健保審查風險 −12 結果：病歷寫得清清楚楚，審查員翻了三小時，最後蓋了個章說「還可以」。 | K3: 【交給行政處理，自己繼續看診】 效果：資金 −NT$ 240,000、聲譽 −8、健保審查風險 +6 結果：行政阿姨硬著頭皮補件，還是少了兩張簽名，罰單寄到了家裡。 | M3: —
A4: 一般 | B4: 原始（events.js） | C4: media_interview | D4: 地方電視台採訪 | E4: 聲譽 ≥ 80 | F4: 否 | G4: 6 | H4: 20 | I4: 地方電視台的記者說想拍「阿伯的膝蓋」專題，問你要不要上鏡頭。 | J4: 【上節目分享復健觀念】 效果：資金 −NT$ 20,000、聲譽 +12 結果：你講得很清楚，還順便教觀眾怎麼做毛巾拉伸。播出後掛號電話快被打爆。 | K4: 【婉拒，專心看病】 效果：聲譽 +1 結果：記者說：「沒關係，我們找隔壁的診所。」你默默看著電視裡的別人。 | M4: —
A5: 診所營運 | B5: 原始（events.js） | C5: poach | D5: 員工被挖角 | E5: 第 1 年起（開業即符合） | F5: 否 | G5: 7 | H5: 20 | I5: 隔壁大醫院的人資私訊你的員工，說薪水可以多兩成，還附停車位。 | J5: 【加薪留人】 效果：資金 −NT$ 200,000、聲譽 +1 結果：員工說「我再想想」，然後留下來了。你的薪資表多了一個零的感覺。 | K5: 【祝他前程似錦】 效果：聲譽 −3、服務點數 −5 結果：員工走了，同事們在茶水間哀嚎：「誰來幫我排班啊！」 | M5: —
A6: 一般 | B6: 原始（events.js） | C6: vendor_promo | D6: 儀器廠商促銷 | E6: 無條件（隨時可能出現） | F6: 否 | G6: 8 | H6: 20 | I6: 儀器業務帶著笑容來：「醫生，這台新機器限時八折，現在下單還送保固！」 | J6: 【買！機器看起來很厲害】（需有資金 NT$ 480,000 以上才可選） 效果：資金 −NT$ 480,000、儀器點數 +20 結果：機器開箱那天，全診所都來拍照。說明書有三百頁，但螢幕很漂亮。 | K6: 【不買，先把舊的顧好】 效果：無數值效果（僅影響劇情） 結果：業務留下名片：「醫生想通了隨時找我喔！」名片你放進抽屜，抽屜很滿。 | M6: —
A7: 季節與在地 | B7: 原始（events.js） | C7: flood | D7: 颱風淹水 | E7: 颱風時 | F7: 否 | G7: 5 | H7: 20 | I7: 颱風過後，馬路變成小河。診所一樓的地板泡在水裡，沙發還在飄。 | J7: 【全體動員清理，搶救設備】（需有資金 NT$ 360,000 以上才可選） 效果：資金 −NT$ 360,000、聲譽 +4 結果：同仁穿雨鞋、拿拖把，忙到半夜。病人隔天來看到，都說「你們很拚」。 | K7: 【停診兩週慢慢修】 效果：資金 −NT$ 160,000、聲譽 −10 結果：招牌上貼著「因故暫停營業」，病人的小本本上多了一個叉叉。 | M7: —
A8: 一般 | B8: 原始（events.js） | C8: pharma_rep | D8: 藥廠業務來訪 | E8: 無條件（隨時可能出現） | F8: 否 | G8: 6 | H8: 20 | I8: 藥廠業務說想請醫生當「學術講者」，一場講座講師費很可觀，但要唸他們的投影片。 | J8: 【接受，去講一場】 效果：資金 +NT$ 240,000、聲譽 −4 結果：講座很順，錢也入袋。只是有位病人在下面小聲問：「醫生，你是在幫哪一家講話？」 | K8: 【婉拒，我們不跟藥廠合作】 效果：聲譽 +3 結果：業務臉色有點難看，但病人們私下說你很正直。 | M8: —
A9: 一般 | B9: 原始（events.js） | C9: fall_lobby | D9: 大廳有人跌倒 | E9: 無條件（隨時可能出現） | F9: 否 | G9: 6 | H9: 20 | I9: 一位阿伯在大廳地板滑了一跤，家屬衝進來大聲問：「你們的地板是怎麼回事？」 | J9: 【立刻送急診，全程陪同】 效果：資金 −NT$ 120,000、聲譽 +6、服務點數 +5 結果：阿伯只是擦傷加扭到腳，家屬紅著眼眶說：「還好你們有處理。」 | K9: 【請家屬簽切結書就好】 效果：聲譽 −12 結果：切結書寫得密密麻麻，家屬簽了，但診所的口碑被寫在大家的 LINE 群組裡。 | M9: —
A10: 一般 | B10: 原始（events.js） | C10: staff_birthday | D10: 護理師生日 | E10: 無條件（隨時可能出現） | F10: 否 | G10: 5 | H10: 20 | I10: 櫃檯護理師生日，同事們想辦個小派對，問醫生能不能出點經費。 | J10: 【全額買蛋糕，犒賞辛苦】 效果：資金 −NT$ 80,000、服務點數 +5 結果：一顆六吋蛋糕被分成二十塊，大家吃到嘴角都是奶油，士氣回升。 | K10: 【大家自己湊錢吧】 效果：聲譽 −1 結果：最後湊出一杯珍奶和一句「生日快樂」。護理師說：「謝謝醫生的心意。」 | M10: —
A11: 一般 | B11: 原始（events.js） | C11: viral_video | D11: 病人影片爆紅 | E11: 聲譽 ≥ 60 | F11: 否 | G11: 4 | H11: 20 | I11: 有病人偷偷拍了你幫他做徒手治療的影片，上傳後居然爆紅，留言一堆「我也要看這醫生」。 | J11: 【順勢拍衛教短片，好好經營】 效果：資金 −NT$ 80,000、聲譽 +15、服務點數 +10 結果：短片教大家「坐久了記得起來動一動」，粉絲破萬，你的名字開始有人念對了。 | K11: 【請病人把影片刪掉】 效果：聲譽 −5 結果：病人很委屈地刪了，但網友已經截圖了一萬次。 | M11: —
A12: 一般 | B12: 原始（events.js） | C12: equip_recall | D12: 儀器召回通知 | E12: 第 1 年起（開業即符合），且有電療儀 | F12: 否 | G12: 4 | H12: 20 | I12: 廠商發通知，你家那台電療儀有安全疑慮要召回，換新機要自費，還附一張道歉信。 | J12: 【立刻換新，安全第一】（需有資金 NT$ 600,000 以上才可選） 效果：資金 −NT$ 600,000、聲譽 +3、儀器點數 +5 結果：新機器亮亮的，病人說「這台看起來比較可靠」，你心裡鬆了一口氣。 | K12: 【先用舊的，觀察看看】 效果：聲譽 −4 結果：病人在候診區問：「那台是不是有問題的那台？」你只能笑笑說還好啦。 | M12: —
A13: 一般 | B13: 原始（events.js） | C13: insurance_sales | D13: 保險業務上門 | E13: 無條件（隨時可能出現） | F13: 否 | G13: 5 | H13: 20 | I13: 保險業務說可以幫員工辦團體醫療險，保費算你們便宜，但要先簽一堆資料。 | J13: 【幫員工加保】 效果：資金 −NT$ 160,000、聲譽 +2 結果：員工收到保單很開心，說「醫生你人真好」。你只好把它當作福利。 | K13: 【婉拒，我自己的保險都看不懂】 效果：無數值效果（僅影響劇情） 結果：業務說：「沒關係，下次再聊！」下次他又來了，你又說不。 | M13: —
... A16: 一般 | B16: 原始（events.js） | C16: parking_fine | D16: 門口被開罰單 | E16: 無條件（隨時可能出現） | F16: 否 | G16: 6 | H16: 20 | I16: 路邊臨停的救護車（不是我們的）被拖吊，里民抱怨說是診所門口讓車子亂停。 | J16: 【請行政去跟交通局溝通】 效果：資金 −NT$ 80,000 結果：行政阿姨跑了三趟區公所，罰單打折了一半，她說以後她要買機車。 | K16: 【在門口貼公告，請大家勿停】 效果：聲譽 −2 結果：公告貼得很漂亮，但車還是停在那裡，大家把公告當成廣告。 | M16: —
A17: 健保營運 | B17: 擴充（events_ext.js） | C17: nhi_ratio_review | D17: 專業審查：等級比例怪怪的 | E17: 第 1 年起（開業即符合），且本月健保點數達上限的 90% 以上 | F17: 是 | G17: 3 | H17: 12 | I17: 審查來函說：「貴所複雜治療占比，和鄰近同儕不太一樣。」主任看著報表，報表也看著主任。 | J17: 【補齊治療紀錄與時間表，全力備審】 效果：資金 −NT$ 50,000、聲譽 +2、健保審查風險 −10 結果：同仁熬夜把每一筆治療的時間表補得整整齊齊，審查員看完點點頭：「這樣就清楚了。」 | K17: 【申覆，賭一把】（擲骰，成功機率 50%） 成功：資金 +NT$ 100,000、聲譽 +3 結果：申覆成功，核減的金額退了回來，主任把那張退款通知裱框掛在櫃檯後面。 失敗：資金 −NT$ 30,000、聲譽 −3、健保點數 −400 點（扣本月申報點數） 結果：申覆沒過，健保點數被扣了四百點，主任說：「賭輸就是輸，下次不賭了。」 | L17: 【認賠，並調整排程】 效果：健保點數 −600 點（扣本月申報點數）、健保審查風險 −15 結果：排程重新排過，複雜治療攤平到每一週，帳上少了一筆錢，多了一本教訓。 | M17: —
A18: 健保營運 | B18: 擴充（events_ext.js） | C18: nhi_growth_flag | D18: 申報成長太快被點名 | E18: 第 2 年起 | F18: 是 | G18: 3 | H18: 24 | I18: 公文寫「近期申報成長幅度較高」，同仁私下說：「我們只是太認真。」 | J18: 【外聘申報顧問做體檢】 效果：資金 −NT$ 150,000、聲譽 +2、健保審查風險 −20 結果：顧問翻了三天帳本，指出兩處寫錯的代碼，還說你們的病歷比他前一個客戶好看。 | K18: 【自己備齊資料】 效果：資金 −NT$ 60,000、聲譽 +1、健保審查風險 −8 結果：行政和護理師熬夜整理資料夾，厚得像一本小說，但每一頁都有簽名。 | L18: 【不理會，生意好是我家的事】（擲骰，成功機率 50%） 成功：無數值效果 結果：這次沒有後續，信件石沉大海，大家鬆了一口氣，只是沒人再敢說生意好。 失敗：聲譽 −6、健保點數 −500 點（扣本月申報點數） 結果：後來還是被抽到，健保點數扣了五百點，主任的生意好論調暫時收了起來。 | M18: —
A19: 健保營運 | B19: 擴充（events_ext.js） | C19: nhi_missing_record | D19: 治療紀錄漏簽 | E19: 無條件（隨時可能出現） | F19: 否 | G19: 6 | H19: 24 | I19: 月底對帳發現三十幾張治療單沒簽名，護理師的筆在抽屜裡集體失蹤。 | J19: 【全員補單週（週末加班）】 效果：全體員工體力 −15、全體員工士氣 −5 結果：週末的診所只剩影印機的聲音，大家一張一張補簽，簽到手都快抽筋。 | K19: 【導入電子簽核表單】 效果：資金 −NT$ 60,000、健保審查風險 −9 結果：電子表單上線第一天就有人問：「這個按鈕是要按哪裡？」不過之後單子就很少漏了。 | L19: 【這些先不報】 效果：健保點數 −300 點（扣本月申報點數） 結果：那幾張單子被收進另一個抽屜，健保點數少了三百點，抽屜倒是變乾淨了。 | M19: —
A20: 健保營運 | B20: 擴充（events_ext.js） | C20: nhi_sixth_visit | D20: 第七次還想只躺不看 | E20: 無條件（隨時可能出現） | F20: 否 | G20: 6 | H20: 24 | I20: 阿嬤第七次報到：「醫生上週才看過啦，我直接躺就好！」 | J20: 【請她掛號，醫師重新評估】 效果：聲譽 +2、全診所病患滿意度 −3（在場病患各 −1.5；接下來一週新來病患的起始滿意度另 −3） 結果：阿嬤嘟嘴去掛號，醫師看了三十秒，說：「你還是要躺，但我要看一下你。」 | K20: 【用簡訊提前預約下次回診】 效果：資金 −NT$ 5,000、聲譽 +1、全診所病患滿意度 +3（在場病患各 +1.5；接下來一週新來病患的起始滿意度另 +3） 結果：簡訊準時送到，阿嬤回了一個貼圖，說：「好啦，知道你們很認真。」 | L20: 【幫她續處方，反正熟】 效果：全診所病患滿意度 +5（在場病患各 +2.5；接下來一週新來病患的起始滿意度另 +5）、健保點數 −200 點（扣本月申報點數）、健保審查風險 +5 結果：阿嬤笑開了花，印章也蓋得很開心，只是健保的眼睛沒有休假。 | M20: —
A21: 健保營運 | B21: 擴充（events_ext.js） | C21: nhi_pt_cap | D21: 治療師今天人次爆表 | E21: 聘有物理治療師（至少 1 位） | F21: 否 | G21: 6 | H21: 24 | I21: 計數器顯示小林治療師今天已經做到第 46 個人，他的手也在抗議。 | J21: 【加聘兼職治療師】 效果：資金 −NT$ 90,000、物理治療師體力 +5 結果：兼職治療師第一天上班，把排程表多看了三遍，總算鬆了一口氣。 | K21: 【限號，超額請改天】 效果：資金 −NT$ 60,000、聲譽 −3、全診所病患滿意度 −6（在場病患各 −3；接下來一週新來病患的起始滿意度另 −6） 結果：超過的病人改天再來，排隊的阿伯有點不高興，說診所是不是要改成抽籤。 | L21: 【照做，超過的當義診】 效果：資金 −NT$ 40,000、物理治療師體力 −12、物理治療師士氣 −4 結果：超量的那幾位病人都免費做完，治療師的手臂抗議到第二天才停。 | M21: —
A22: 健保營運 | B22: 擴充（events_ext.js） | C22: nhi_role_mismatch | D22: 誰做的治療就報誰 | E22: 聘有職能治療師（至少 1 位），且聘有物理治療師（至少 1 位） | F22: 是 | G22: 3 | H22: 24 | I22: 行政發現早療的申報代碼，和實際執行的人對不上，兩邊都說：「我以為你會改。」 | J22: 【立刻內部稽核，更正歷史申報】 效果：資金 −NT$ 40,000、聲譽 +2、健保審查風險 −10 結果：稽核人員連夜翻出三個月的紀錄，更正單一張張蓋章，整間診所像開了一場小型會議。 | K22: 【補聘 PT 專責，OT 專做職能】 效果：資金 −NT$ 100,000、服務點數 +5 結果：新來的治療師負責早療的大動作，職能治療師也能專心做精細動作，小朋友笑得很開心。 | L22: 【名稱而已啦】（擲骰，成功機率 70%） 成功：無數值效果 結果：這次沒被查到，大家鬆了一口氣，只是名字的小差異還在那裡等著。 失敗：資金 −NT$ 300,000、聲譽 −10 結果：有人來查，發現代碼跟人對不上，罰單寄到門口，主任還在說：「只是名稱而已啦。」 | M22: —
A23: 健保營運 | B23: 擴充（events_ext.js） | C23: nhi_neighbor_fraud | D23: 同業被終止特約的新聞 | E23: 聲譽 ≥ 40 | F23: 否 | G23: 6 | H23: 24 | I23: 新聞說某區有診所「補卡刷兩次」被停約，阿嬤們到處問：「你們有沒有這樣？」 | J23: 【貼公告：一律先診察、不重複刷卡】 效果：資金 −NT$ 10,000、聲譽 +4 結果：公告貼在掛號櫃檯旁，阿嬤看了點頭：「這樣我就放心了。」 | K23: 【只回答「我們合法啦」】 效果：聲譽 +1 結果：阿嬤回去跟鄰居說醫生說他們合法，鄰居問：「那有沒有被罰？」阿嬤說：「沒問。」 | L23: 【趁機接收對方流失的病人】 效果：「同業流失病人」加成，持續 4 週（約 1 個月）：來客量 +10%、全體員工體力 −8 結果：有幾位病人被新聞嚇到，轉來這裡，同仁忙到腳都站麻了。 | M23: —
A24: 健保營運 | B24: 擴充（events_ext.js） | C24: nhi_pv_drop | D24: 季點值下滑 | E24: 3、6、9、12 月，且上月健保點值低於 0.9 | F24: 否 | G24: 6 | H24: 36 | I24: 季結算單寄到：點值又掉了。會計小姐說：「我們賣得越多，每點越不值錢。」 | J24: 【看板加強自費說明，推有用的自費項目】 效果：資金 −NT$ 30,000、「自費說明看板」加成，持續 6 週（約 2 個月）：自費轉換率 +4% 結果：看板上的自費項目排得整整齊齊，有位阿姨說：「原來這個有用喔？」 | K24: 【控制健保量，減少電熱療排程】 效果：「控制健保量」加成，持續 4 週（約 1 個月）：來客量 −10% 結果：電熱療的排程變少了，候診室安靜不少，點值沒有立刻變好，心情倒是變好了。 | L24: 【先吞下去】 效果：全體員工士氣 −5 結果：大家都沒說話，只是把計算機又按了一次，數字還是一樣。 | M24: —
A25: 健保營運 | B25: 擴充（events_ext.js） | C25: nhi_clawback | D25: 暫付金額被追回 | E25: 3、6、9、12 月 | F25: 是 | G25: 3 | H25: 36 | I25: 公文寫「暫付與結算差額」，老闆看了三遍，數字沒有變。 | J25: 【早就提列準備金】 效果：資金 −NT$ 100,000 結果：準備金早就在帳上等著，追回的金額來的時候，會計只淡淡地說：「有準備就不慌。」 | K25: 【照樣花，扣到再說】 效果：資金 −NT$ 200,000 結果：帳戶餘額像退潮一樣往下掉，老闆開始每天早上先看銀行，才敢喝咖啡。 | L25: 【申請分期】 效果：資金 −NT$ 40,000 結果：分期的利息不便宜，但現金流總算能喘口氣，只是每個月都要記得還。 | M25: —
A26: 健保營運 | B26: 擴充（events_ext.js） | C26: nhi_survey_call | D26: 健保來電訪問病人 | E26: 第 1 年起（開業即符合） | F26: 否 | G26: 6 | H26: 16 | I26: 阿伯接到電話被問：「你上禮拜有去復健嗎？」他回頭問櫃檯：「我有去嗎？」 | J26: 【告訴病人：據實回答就好】 效果：聲譽 +3 結果：病人開始照實回答，電話那頭的訪員也說：「原來是這樣喔，謝謝你。」 | K26: 【請同仁整理到診紀錄，備查】 效果：資金 −NT$ 10,000、健保審查風險 −5 結果：病歷室的資料夾排得很整齊，每一通電話都能對得上日期。 | L26: 【提醒大家「怎麼回答比較好」】（擲骰，成功機率 50%） 成功：無數值效果 結果：這次沒被發現，同仁互相看了一眼，誰也不敢再提這句話。 失敗：聲譽 −8、健保點數 −400 點（扣本月申報點數） 結果：被發現了，訪問紀錄寫得清清楚楚，健保點數扣了四百點。 | M26: —
A27: 健保營運 | B27: 擴充（events_ext.js） | C27: nhi_regular_guest | D27: 回診拿熱敷的常客 | E27: 無條件（隨時可能出現） | F27: 否 | G27: 6 | H27: 24 | I27: 阿伯每週三準時報到，熱敷、聊天、順便評論診所椅子，已經變成里的新聞台。 | J27: 【評估後改運動處方，教居家運動】 效果：聲譽 +4、醫術點數 +5、全診所病患滿意度 −4（在場病患各 −2；接下來一週新來病患的起始滿意度另 −4） 結果：阿伯被教了五套居家運動，抱怨了三天，第四天就開始自己做了。 | K27: 【轉介社區活動據點】 效果：聲譽 +5、全診所病患滿意度 −2（在場病患各 −1；接下來一週新來病患的起始滿意度另 −2） 結果：阿伯去了社區據點，跟一群阿伯阿嬤下棋，回診少了，話題多了。 | L27: 【照單全收】 效果：資金 +NT$ 40,000、聲譽 −2、健保審查風險 +6 結果：熱敷的鐘聲一響，阿伯又來了，報表上多了一排數字，風評則悄悄少了一點。 | M27: —
A28: 健保營運 | B28: 擴充（events_ext.js） | C28: nhi_evidence_news | D28: 新聞說電熱療效果有限 | E28: 聲譽 ≥ 30 | F28: 否 | G28: 6 | H28: 24 | I28: 候診室電視在播「電療熱療只能暫時舒緩」，所有人同時看向護理師。 | J28: 【改版療程：被動治療搭配運動治療】 效果：資金 −NT$ 40,000、聲譽 +4、醫術點數 +8 結果：療程表多了運動課，候診的阿伯問：「原來要動才會好喔？」護理師說：「對，還是要動。」 | K28: 【衛教說明被動治療的角色】 效果：資金 −NT$ 5,000、聲譽 +2 結果：衛教單寫得很清楚：被動治療是輔助，不是主角，阿姨們說這樣就放心了。 | L28: 【不理會】 效果：全診所病患滿意度 −3（在場病患各 −1.5；接下來一週新來病患的起始滿意度另 −3） 結果：電視還在播，候診的病人一臉懷疑，接下來幾天的滿意度也跟著往下掉。 | M28: —
... A74: 季節與在地 | B74: 擴充（events_ext2.js） | C74: yearend_office_crunch | D74: 年終加班的肩頸 | E74: 11–12 月 | F74: 否 | G74: 10 | H74: 44 | I74: 上班族說：「年終前不能請假，我的脖子可以請假嗎？」 | J74: 【辦企業到點衛教】（需有資金 NT$ 50,000 以上才可選） 效果：資金 −NT$ 50,000、聲譽 +4、「企業到點衛教」加成，持續 4 週（約 1 個月）：肩頸僵硬上班族來客 +30% 結果：衛教師到公司講解伸展，員工一起轉脖子，會議室像在做體操。 | K74: 【午休線上衛教】（需有資金 NT$ 10,000 以上才可選） 效果：資金 −NT$ 10,000、聲譽 +2 結果：午休影片一播，大家邊吃便當邊轉肩膀，脖子終於有空休息一下。 | L74: 【不辦】 效果：無數值效果（僅影響劇情） 結果：年終前夕，大家繼續低頭打字，脖子跟著低頭。 | M74: —

Sheet 天氣
A1: 名稱 | B1: id | C1: 圖示 | D1: 出現月份 | E1: 抽選權重 | F1: 氣溫範圍 | G1: 對病患／滑倒／來客的影響 | H1: 一句新聞
A2: 晴朗好天氣 | B2: sunny | C2: ☀️ | D2: 3–11 月 | E2: 30 | F2: 24–33°C | G2: 運動傷害病患來客 ×1.3；晨間長輩團來客 ×1.05；滑倒機率 ×0.9 | H2: 陽光超猛，運動員都出來跑步了，膝蓋也跟著出門。
A3: 陰天 | B3: cloudy | C3: ☁️ | D3: 1–12 月 | E3: 25 | F3: 20–28°C | G3: 肩頸僵硬上班族來客 ×1.1；滑倒機率不變 | H3: 陰陰的，不晴不雨，上班族的肩頸先陰了。
A4: 午後陣雨 | B4: rain | C4: 🌦️ | D4: 3–5、9–11 月 | E4: 18 | F4: 21–28°C | G4: 晨間長輩團來客 ×1.2；滑倒機率 ×1.5 | H4: 午後一陣雨，地板濕濕的，走路要看路喔。
A5: 梅雨季 | B5: plumrain | C5: 🌧️ | D5: 5–6 月 | E5: 40 | F5: 21–28°C | G5: 晨間長輩團來客 ×1.25；肩頸僵硬上班族來客 ×0.9；滑倒機率 ×1.6；員工體力消耗 +10% | H5: 梅雨下不停，衣服半乾不溼，關節也是。同仁說身體像泡過水。
A6: 寒流來襲 | B6: cold | C6: 🥶 | D6: 12–2 月 | E6: 30 | F6: 8–16°C | G6: 晨間長輩團來客 ×1.6；肩頸僵硬上班族來客 ×0.95；滑倒機率 ×1.3 | H6: 寒流來了！阿伯阿嬤的膝蓋和肩膀準時報到。
A7: 炎夏高溫 | B7: hot | C7: 🥵 | D7: 7–8 月 | E7: 25 | F7: 31–38°C | G7: 運動傷害病患來客 ×0.8；早療兒童與家長來客 ×0.7；晨間長輩團來客 ×0.9；滑倒機率不變；員工體力消耗 +20%；來客量 −10% | H7: 熱到柏油路會軟，大家都躲在冷氣房裡，運動的人也少了。
A8: 颱風警報 | B8: typhoon | C8: 🌀 | D8: 7–10 月 | E8: 6 | F8: 24–30°C | G8: 滑倒機率 ×1.2；來客量 −60% | H8: 颱風天停班停課，病人都待在家，診所冷冷清清，只剩風在唱歌。

Sheet 醫病溝通兩難
A1: 觸發（病患的要求） | B1: id | C1: 標題 | D1: 適用病患 | E1: 情境 | F1: 選項1 | G1: 選項2 | H1: 選項3
A2: 病患要求直接開止痛藥／止痛針 | B2: painkiller_elder | C2: 「直接開止痛藥就好啦」 | D2: 晨間長輩團 | E2: 阿伯揉著膝蓋說：「醫生啊，不要囉嗦那麼多，你直接開止痛藥給我就好啦。」 | F2: 【好，先開止痛藥給你】 效果：聲譽 −4、該病患滿意度 +8 結果：阿伯笑瞇瞇拿藥走，三天後又回來說「還是痛」。你心裡有點酸酸的。 | G2: 【先評估，再一起決定療程】 效果：聲譽 +4、該病患滿意度 −6 結果：阿伯不太開心地嘟嚷：「我只是要藥。」但他還是乖乖躺上床做了評估。
A3: 病患要求直接開止痛藥／止痛針 | B3: painkiller_office | C3: 「醫生，上班好忙，給我止痛藥啦」 | D3: 肩頸僵硬上班族 | E3: 上班族一臉疲憊：「醫生，我今天還要開會，你就給我一顆止痛藥，拜託。」 | F3: 【開藥，但也排個熱敷】 效果：聲譽 −2、該病患滿意度 +5 結果：他很感激你的熱敷，但回家路上還是覺得你「有點囉嗦」。 | G3: 【告訴他止痛藥不能亂吃】 效果：聲譽 +3、該病患滿意度 −4 結果：他嘆了口氣說：「好吧，那我去買別家的。」你覺得自己做對了，但胃有點痛。
A4: 病患要求直接開止痛藥／止痛針 | B4: painkiller_sports | C4: 「明天要比賽，打一針止痛針」 | D4: 運動傷害病患 | E4: 業餘選手的眼神很堅定：「醫生，明天就是大賽，你給我打一針，我不怕痛。」 | F4: 【不行，先評估傷勢再說】 效果：聲譽 +5、醫術點數 +3、該病患滿意度 −4 結果：選手很不爽地走了，但隔週他回來說：「還好你擋我，那天我真的會受傷。」 | G4: 【打！他說不怕就讓他打】 效果：聲譽 −10、該病患滿意度 +10、健保點數 −200 點（扣本月申報點數） 結果：比賽當天他拿了第三名，朋友們都說：「是你們診所的功勞！」傳言也因此開始走樣。
A5: 病患想跳過醫師評估，只要做電療或震波 | B5: skip_doctor_elder | C5: 「我只要電療，不要看醫生」 | D5: 晨間長輩團 | E5: 阿嬤一進門就說：「我只要去躺電療，醫生就不用看啦，很麻煩耶。」 | F5: 【依規定，先看醫生再做電療】 效果：聲譽 +3、該病患滿意度 −5 結果：阿嬤碎碎唸了半小時，最後還是乖乖去看醫生，她說：「好啦，醫生你很煩。」 | G5: 【同意，但病歷上註記清楚】 效果：聲譽 −2、該病患滿意度 +4、健保點數 −200 點（扣本月申報點數） 結果：阿嬤很開心地躺上電療床，你的良心卻被健保署的表格默默記了一筆。
A6: 病患想跳過醫師評估，只要做電療或震波 | B6: skip_doctor_office | C6: 「只想做震波，時間很趕」 | D6: 肩頸僵硬上班族 | E6: 上班族看了看手錶：「醫生，我不想看醫生了，我直接做震波就好，我只有半小時。」 | F6: 【震波可以做，但要先過一下評估】 效果：聲譽 +2、該病患滿意度 +2 結果：他說「好吧，那就快一點」，評估花了五分鐘，震波打完他說：「還真有差！」 | G6: 【收自費，直接排震波】 效果：資金 +NT$ 80,000、聲譽 −4、該病患滿意度 +3 結果：收據很漂亮，但同事小聲說：「我們好像把流程跳過了。」
A7: 病患要求過度治療（次數或堂數超過建議） | B7: overtreat_elder | C7: 「醫生，我想每天來做八次熱敷」 | D7: 晨間長輩團 | E7: 阿伯很認真地問：「每天做八次熱敷，會不會比較快好？我可以每天都來吧？」 | F7: 【依病情調整頻率，每週幾次就好】 效果：聲譽 +4、該病患滿意度 −3 結果：阿伯有點失望，但也慢慢接受：「原來不是越多越好喔。」 | G7: 【好，每天做，收費照算】 效果：資金 +NT$ 120,000、聲譽 −8、健保點數 −300 點（扣本月申報點數） 結果：帳單很漂亮，健保署的審查委員看到的時候，眉毛挑得很高。
A8: 病患要求過度治療（次數或堂數超過建議） | B8: overtreat_self | C8: 「我想一次買十堂震波課程」 | D8: 通用（同類情境隨機抽取） | E8: 老闆一拍桌：「醫生，我想一次買十堂震波，有沒有折扣？我全部都要！」 | F8: 【依病情建議三堂就夠】 效果：聲譽 +3 結果：老闆說：「醫生你很誠實耶，我下次介紹朋友來。」 | G8: 【給他十堂，收錢收到手軟】 效果：資金 +NT$ 320,000、聲譽 −10 結果：帳戶多了一大筆錢，但老闆做到第四堂就說不痛了，之後再也沒來過。
A9: 病患要求過度治療（次數或堂數超過建議） | B9: overtreat_kid | C9: 「我家小孩每天都要來感統」 | D9: 早療兒童與家長 | E9: 家長很堅持：「我家小孩每天都要來做感統，他很愛玩球池，你可以排滿一點吧？」 | F9: 【依發展評估，一週兩到三次】 效果：聲譽 +3、服務點數 +3、該病患滿意度 −2 結果：家長嘆氣說：「好吧，那週末可以多來一次嗎？」你說週末我們也有門診。 | G9: 【每天排滿，收費照算】 效果：資金 +NT$ 160,000、聲譽 −6 結果：小朋友玩得超開心，但家長在群組裡問：「為什麼感統一定要每天來？」
A10: 病患當面投訴（等太久、收費、機器、態度） | B10: complain_wait | C10: 「等了一個半小時，你們怎麼排的！」 | D10: 通用（同類情境隨機抽取） | E10: 阿姨拍著掛號櫃檯大喊：「我一個半小時了耶！你們到底是怎麼排班的啦！」 | F10: 【真誠道歉，免費加送一次熱敷】 效果：資金 −NT$ 32,000、聲譽 +2、該病患滿意度 +10 結果：阿姨嘴上說「下次不要這樣」，但熱敷時已經靠在枕頭上打呼了。 | G10: 【解釋今天很忙，請她耐心等】 效果：聲譽 −6、該病患滿意度 −15 結果：阿姨說：「我下次去大醫院！」背影有種不回頭的堅定。
A11: 病患當面投訴（等太久、收費、機器、態度） | B11: complain_price | C11: 「為什麼要自費？健保不能做嗎？」 | D11: 通用（同類情境隨機抽取） | E11: 阿伯看著自費單，眉頭皺成一團：「醫生，健保不能做嗎？為什麼要我自己付錢？」 | F11: 【說明健保與自費差異，附上書面說明】 效果：聲譽 +2、該病患滿意度 +4 結果：阿伯看完說：「原來是這樣，我還以為你們是在騙錢。」你默默把說明書多印了五十張。 | G11: 【直接說健保沒有這項】 效果：聲譽 −3、該病患滿意度 −6 結果：阿伯不滿地走了，但他家的小孫子在候診區偷偷把這句話錄起來。 | H11: 【這次先不收費，給個人情】 效果：資金 −NT$ 60,000、該病患滿意度 +8 結果：阿伯很感動，回去跟鄰居說你們「很有人情味」，但你的帳本少了一筆。
A12: 病患當面投訴（等太久、收費、機器、態度） | B12: complain_noisy | C12: 「電療機器嗡嗡叫，我頭很痛」 | D12: 通用（同類情境隨機抽取） | E12: 阿嬤躺在電療床上皺眉：「醫生，這台機器一直嗡嗡叫，我頭好痛，是不是壞了？」 | F12: 【換一台新機器，給她看】 效果：資金 −NT$ 240,000、聲譽 +2、該病患滿意度 +6 結果：阿嬤摸著新機器說：「這台比較安靜，好很多。」你偷偷把舊機器的螺絲拆下來留著。 | G12: 【請她忍耐一下，治療很快就好】 效果：聲譽 −2、該病患滿意度 −8 結果：阿嬤嘆氣：「忍耐、忍耐，我都忍一輩子了。」你覺得這句話好重。
A13: 病患當面投訴（等太久、收費、機器、態度） | B13: complain_staff | C13: 「你們護理師態度很差！」 | D13: 通用（同類情境隨機抽取） | E13: 一位病人投訴護理師講話太大聲，還說「你們是在趕人嗎？」 | F13: 【調查後處理，當面道歉】 效果：資金 −NT$ 20,000、聲譽 +4、該病患滿意度 +5 結果：護理師紅著眼眶說：「我以後會注意語氣。」病人說：「有道歉就好。」 | G13: 【護理師沒有錯，請病人多包涵】 效果：聲譽 −4、該病患滿意度 −8 結果：病人在網路上寫了一篇長文，標題是「這家診所，我不推」。

Sheet 社區活動
A1: 活動 | B1: id | C1: 說明 | D1: 費用（NT$） | E1: 持續（週） | F1: 冷卻（週，開辦後） | G1: 立即效果 | H1: 活動期間效果
A2: 宮廟肌少症篩檢 | B2: temple_sarcopenia | C2: 廟埕擺攤量握力、測步速，阿嬤們排隊排到拜拜的香爐旁。 | D2: 75000 | E2: 2 | F2: 6 | G2: 聲譽 +5、服務點數 +10 | H2: 晨間長輩團來客 +30%
A3: 社區衛教講座 | B3: health_talk | C3: 社區活動中心的小講座，教大家正確的姿勢與熱敷觀念。 | D3: 30000 | E3: 2 | F3: 4 | G3: 聲譽 +3、服務點數 +8 | H3: 肩頸僵硬上班族來客 +10%、晨間長輩團來客 +10%
A4: 校園脊椎側彎篩檢 | B4: school_scoliosis | C4: 國小體檢後來一波側彎篩檢，家長聽到「要不要來看看」都緊張兮兮。 | D4: 120000 | E4: 3 | F4: 8 | G4: 聲譽 +6、醫術點數 +10、服務點數 +5 | H4: 早療兒童與家長來客 +40%
A5: 公司健康促進講座 | B5: company_health | C5: 到科技公司的會議室講坐著工作的痠痛，同仁一邊聽一邊偷偷伸懶腰。 | D5: 105000 | E5: 2 | F5: 6 | G5: 聲譽 +4、服務點數 +8 | H5: 肩頸僵硬上班族來客 +35%
A6: 里民健走活動 | B6: village_walk | C6: 每天早上繞里內走一圈，阿伯阿嬤帶著保溫杯，運動員也跟著跑。 | D6: 45000 | E6: 4 | F6: 4 | G6: 聲譽 +3、服務點數 +6 | H6: 晨間長輩團來客 +20%、運動傷害病患來客 +20%
A7: 長照據點合作 | B7: ltc_partner | C7: 和社區長照據點簽約，每週定期去帶動能運動，阿嬤們說比去大樓下棋還好玩。 | D7: 240000 | E7: 6 | F7: 10 | G7: 聲譽 +12、服務點數 +20、醫術點數 +5 | H7: 晨間長輩團來客 +50%
A8: 夜市路跑熱身站 | B8: night_run | C8: 在夜市出口設熱身站，發小冰棒、貼運動貼布，順便幫跑者看看膝蓋。 | D8: 90000 | E8: 2 | F8: 6 | G8: 聲譽 +6、醫術點數 +5 | H8: 運動傷害病患來客 +40%

Sheet 衛教看板
A1: 看板 | B1: id | C1: 說明 | D1: 安裝費（NT$，一次） | E1: 每月維護費（NT$） | F1: 效果（看板開啟期間）
A2: 護腰護膝篇 | B2: back_knee | C2: 看板教大家躺下、起身的正確姿勢，候診的人看著看著就忘了等待的煩躁。 | D2: 24000 | E2: 1500 | F2: 病患耐心 +5%
A3: 冷熱敷觀念 | B3: hot_cold | C3: 急性扭傷先冰、慢性痠痛才熱，看板講得很白話，大家都說「原來如此」。 | D3: 18000 | E3: 900 | F3: 自費轉換率 +2%
A4: 兒童發展里程碑 | B4: kid_milestone | C4: 幾個月會翻身、幾歲會跑跳，家長對照著看，焦慮少了，來問問題的也變多了。 | D4: 45000 | E4: 1200 | F4: 病患耐心 +5%、點數獲得 +2%
A5: 長者防跌五招 | B5: elder_fall | C5: 起床先坐五秒、浴室加扶手、拖鞋要穿好。阿嬤拍照存進 LINE 群組。 | D5: 36000 | E5: 1200 | F5: 滑倒風險 −10%、長輩滿意度 +2
A6: 自費項目說明 | B6: selfpay_explain | C6: 健保與自費差在哪、值不值得，寫清楚講明白，「為什麼要自費」少被問一次。 | D6: 30000 | E6: 900 | F6: 自費轉換率 +4%
A7: 長輩營養與肌少症 | B7: elder_nutrition | C7: 吃足蛋白質、多曬太陽、動一動。阿公說：「原來不是老了才會沒力。」 | D7: 60000 | E7: 1500 | F7: 長輩滿意度 +3
A8: 久坐族的頸肩操 | B8: office_posture | C8: 每小時起來伸個懶腰，看板上的小人偶跟你一起抖肩。上班族笑著拍了照。 | D8: 27000 | E8: 900 | F8: 病患耐心 +3%、自費轉換率 +1%

Sheet 成就
A1: 分類 | B1: 名稱 | C1: id | D1: 階層 | E1: 階層序 | F1: 條件 | G1: 獎勵：資金（NT$） | H1: 獎勵：聲譽 | I1: 獎勵：點數種類 | J1: 獎勵：點數 | K1: 獎勵摘要 | L1: 徽章 | M1: 附贈稱號 | N1: 隱藏 | O1: 提示（隱藏成就） | P1: 進度（目標）
A2: 經營里程碑 | B2: 開張大吉 | C2: m_first_month | D2: 銅 | E2: 1 | F2: 完成第一次月底健保結算。 | G2: 10000 | H2: 0 | I2: 服務 | J2: 8 | K2: 資金 +NT$ 10,000、服務點數 +8 | L2: 🎉 | M2: — | N2: 否 | O2: — | P2: —
A3: 經營里程碑 | B3: 第一桶金 | C3: m_cash_2m | D3: 銅 | E3: 1 | F3: 資金累積到 NT$ 2,000,000 以上。 | G3: 10000 | H3: 0 | I3: 服務 | J3: 8 | K3: 資金 +NT$ 10,000、服務點數 +8 | L3: 💰 | M3: — | N3: 否 | O3: — | P3: 資金（目標 2,000,000）
A4: 經營里程碑 | B4: 千萬院長 | C4: m_cash_10m | D4: 金 | E4: 3 | F4: 資金累積到 NT$ 10,000,000 以上。 | G4: 150000 | H4: 10 | I4: 服務 | J4: 30 | K4: 資金 +NT$ 150,000、聲譽 +10、服務點數 +30 | L4: 💎 | M4: 千萬院長 | N4: 否 | O4: — | P4: 資金（目標 10,000,000）
A5: 經營里程碑 | B5: 百人次 | C5: m_pat_100 | D5: 銅 | E5: 1 | F5: 累計服務 100 位病患。 | G5: 10000 | H5: 0 | I5: 服務 | J5: 8 | K5: 資金 +NT$ 10,000、服務點數 +8 | L5: 👥 | M5: — | N5: 否 | O5: — | P5: 累計服務病患（目標 100）
A6: 經營里程碑 | B6: 千人次 | C6: m_pat_1000 | D6: 銀 | E6: 2 | F6: 累計服務 1,000 位病患。 | G6: 35000 | H6: 3 | I6: 服務 | J6: 15 | K6: 資金 +NT$ 35,000、聲譽 +3、服務點數 +15 | L6: 👥 | M6: — | N6: 否 | O6: — | P6: 累計服務病患（目標 1,000）
A7: 經營里程碑 | B7: 五千人次 | C7: m_pat_5000 | D7: 金 | E7: 3 | F7: 累計服務 5,000 位病患。 | G7: 150000 | H7: 10 | I7: 服務 | J7: 30 | K7: 資金 +NT$ 150,000、聲譽 +10、服務點數 +30 | L7: 🌟 | M7: 在地萬人迷 | N7: 否 | O7: — | P7: 累計服務病患（目標 5,000）
A8: 經營里程碑 | B8: 妙手回春 | C8: m_cured_100 | D8: 銀 | E8: 2 | F8: 累計治癒 100 位病患。 | G8: 35000 | H8: 3 | I8: 醫術 | J8: 15 | K8: 資金 +NT$ 35,000、聲譽 +3、醫術點數 +15 | L8: ✋ | M8: 妙手回春 | N8: 否 | O8: — | P8: 累計治癒病患（目標 100）
A9: 經營里程碑 | B9: 口碑起家 | C9: m_rep_100 | D9: 銅 | E9: 1 | F9: 聲譽達到 100 以上。 | G9: 10000 | H9: 0 | I9: 服務 | J9: 8 | K9: 資金 +NT$ 10,000、服務點數 +8 | L9: 📣 | M9: — | N9: 否 | O9: — | P9: 聲譽（目標 100）
A10: 經營里程碑 | B10: 地方名醫 | C10: m_rep_250 | D10: 銀 | E10: 2 | F10: 聲譽達到 250 以上。 | G10: 35000 | H10: 3 | I10: 服務 | J10: 15 | K10: 資金 +NT$ 35,000、聲譽 +3、服務點數 +15 | L10: 📣 | M10: — | N10: 否 | O10: — | P10: 聲譽（目標 250）
A11: 經營里程碑 | B11: 全國有名 | C11: m_rep_600 | D11: 金 | E11: 3 | F11: 聲譽達到 600 以上。 | G11: 150000 | H11: 10 | I11: 服務 | J11: 30 | K11: 資金 +NT$ 150,000、聲譽 +10、服務點數 +30 | L11: 🎖️ | M11: 國民復健名醫 | N11: 否 | O11: — | P11: 聲譽（目標 600）
A12: 經營里程碑 | B12: 搬新家 | C12: m_lot1 | D12: 銅 | E12: 1 | F12: 擴建到「社區診所」。 | G12: 10000 | H12: 0 | I12: 服務 | J12: 8 | K12: 資金 +NT$ 10,000、服務點數 +8 | L12: 🏠 | M12: — | N12: 否 | O12: — | P12: —
A13: 經營里程碑 | B13: 擴大營業 | C13: m_lot2 | D13: 銀 | E13: 2 | F13: 擴建到「地區復健中心」。 | G13: 35000 | H13: 3 | I13: 服務 | J13: 15 | K13: 資金 +NT$ 35,000、聲譽 +3、服務點數 +15 | L13: 🏢 | M13: — | N13: 否 | O13: — | P13: —
... A42: 挑戰與隱藏 | B42: 叢林診所 | C42: h_plants | D42: 銅 | E42: 1 | F42: 同時擺放 10 盆綠植。 | G42: 10000 | H42: 0 | I42: 服務 | J42: 8 | K42: 資金 +NT$ 10,000、服務點數 +8 | L42: 🌿 | M42: — | N42: 是 | O42: 診所裡的綠意越來越濃，快變成森林了？ | P42: —
